dagster_ext/__init__.py
dagster_ext/extension.py
dagster_ext/main.py
dagster_ext/pass_through.py
files_dagster_ext/dagster/cookiecutter.json
files_dagster_ext/dagster/{{ cookiecutter.project_name }}/repository.py
files_dagster_ext/github/cookiecutter.json
meltano/edk/__init__.py
meltano/edk/extension.py
meltano/edk/logging.py
meltano/edk/models.py
meltano/edk/process.py
elt_dagster_ext-1.0.0.dist-info/METADATA
elt_dagster_ext-1.0.0.dist-info/WHEEL
elt_dagster_ext-1.0.0.dist-info/entry_points.txt
elt_dagster_ext-1.0.0.dist-info/RECORD
